StreamingCommunity/__init__.py
StreamingCommunity/__main__.py
StreamingCommunity/global_search.py
StreamingCommunity/run.py
StreamingCommunity/Api/Player/mediapolisvod.py
StreamingCommunity/Api/Player/supervideo.py
StreamingCommunity/Api/Player/sweetpixel.py
StreamingCommunity/Api/Player/vixcloud.py
StreamingCommunity/Api/Service/altadefinizione/__init__.py
StreamingCommunity/Api/Service/altadefinizione/film.py
StreamingCommunity/Api/Service/altadefinizione/series.py
StreamingCommunity/Api/Service/altadefinizione/site.py
StreamingCommunity/Api/Service/altadefinizione/util/ScrapeSerie.py
StreamingCommunity/Api/Service/animeunity/__init__.py
StreamingCommunity/Api/Service/animeunity/film.py
StreamingCommunity/Api/Service/animeunity/serie.py
StreamingCommunity/Api/Service/animeunity/site.py
StreamingCommunity/Api/Service/animeunity/util/ScrapeSerie.py
StreamingCommunity/Api/Service/animeworld/__init__.py
StreamingCommunity/Api/Service/animeworld/film.py
StreamingCommunity/Api/Service/animeworld/serie.py
StreamingCommunity/Api/Service/animeworld/site.py
StreamingCommunity/Api/Service/animeworld/util/ScrapeSerie.py
StreamingCommunity/Api/Service/crunchyroll/__init__.py
StreamingCommunity/Api/Service/crunchyroll/film.py
StreamingCommunity/Api/Service/crunchyroll/series.py
StreamingCommunity/Api/Service/crunchyroll/site.py
StreamingCommunity/Api/Service/crunchyroll/util/ScrapeSerie.py
StreamingCommunity/Api/Service/crunchyroll/util/client.py
StreamingCommunity/Api/Service/crunchyroll/util/get_license.py
StreamingCommunity/Api/Service/discovery/__init__.py
StreamingCommunity/Api/Service/discovery/series.py
StreamingCommunity/Api/Service/discovery/site.py
StreamingCommunity/Api/Service/discovery/util/ScrapeSerie.py
StreamingCommunity/Api/Service/discovery/util/get_license.py
StreamingCommunity/Api/Service/discoveryeu/__init__.py
StreamingCommunity/Api/Service/discoveryeu/series.py
StreamingCommunity/Api/Service/discoveryeu/site.py
streamingcommunity-3.5.6.dist-info/licenses/LICENSE
streamingcommunity-3.5.6.dist-info/METADATA
streamingcommunity-3.5.6.dist-info/WHEEL
streamingcommunity-3.5.6.dist-info/entry_points.txt
streamingcommunity-3.5.6.dist-info/top_level.txt
streamingcommunity-3.5.6.dist-info/RECORD
