Metadata-Version: 2.4
Name: StreamingCommunity
Version: 3.5.6
Summary: Download content from streaming platforms
Home-page: https://github.com/Arrowar/StreamingCommunity
Author: Arrowar
Project-URL: Bug Reports, https://github.com/Arrowar/StreamingCommunity/issues
Project-URL: Source, https://github.com/Arrowar/StreamingCommunity
Classifier: Development Status :: 4 - Beta
Classifier: Intended Audience :: End Users/Desktop
Classifier: Programming Language :: Python :: 3
Classifier: Programming Language :: Python :: 3.8
Classifier: Programming Language :: Python :: 3.9
Classifier: Programming Language :: Python :: 3.10
Classifier: Programming Language :: Python :: 3.11
Classifier: Programming Language :: Python :: 3.12
Classifier: Operating System :: OS Independent
Requires-Python: >=3.8
License-File: LICENSE
Dynamic: author
Dynamic: classifier
Dynamic: description
Dynamic: description-content-type
Dynamic: home-page
Dynamic: license-file
Dynamic: project-url
Dynamic: requires-python
Dynamic: summary
